corlib/__init__.py
corlib/example.py
corlib-0.0.1.dist-info/METADATA
corlib-0.0.1.dist-info/WHEEL
corlib-0.0.1.dist-info/licenses/LICENSE
corlib-0.0.1.dist-info/RECORD
